autodistill_siglip/__init__.py
autodistill_siglip/siglip_model.py
autodistill_siglip-0.1.0.dist-info/METADATA
autodistill_siglip-0.1.0.dist-info/WHEEL
autodistill_siglip-0.1.0.dist-info/top_level.txt
autodistill_siglip-0.1.0.dist-info/RECORD
